sagemaker_studio_analytics_extension/__init__.py
sagemaker_studio_analytics_extension/external_dependencies/__init__.py
sagemaker_studio_analytics_extension/external_dependencies/emr_serverless_auth.py
sagemaker_studio_analytics_extension/magics/__init__.py
sagemaker_studio_analytics_extension/magics/sagemaker_analytics.py
sagemaker_studio_analytics_extension/patches/configuration.py
sagemaker_studio_analytics_extension/patches/reliablehttpclient.py
sagemaker_studio_analytics_extension/resource/__init__.py
sagemaker_studio_analytics_extension/resource/resource_metadata.py
sagemaker_studio_analytics_extension/resource/emr/__init__.py
sagemaker_studio_analytics_extension/resource/emr/auth.py
sagemaker_studio_analytics_extension/resource/emr/emr_client.py
sagemaker_studio_analytics_extension/resource/emr_serverless/emr_s_client.py
sagemaker_studio_analytics_extension/utils/__init__.py
sagemaker_studio_analytics_extension/utils/arn_util.py
sagemaker_studio_analytics_extension/utils/boto_client_utils.py
sagemaker_studio_analytics_extension/utils/client_factory.py
sagemaker_studio_analytics_extension/utils/client_interface.py
sagemaker_studio_analytics_extension/utils/common_utils.py
sagemaker_studio_analytics_extension/utils/constants.py
sagemaker_studio_analytics_extension/utils/emr_constants.py
sagemaker_studio_analytics_extension/utils/emr_serverless_magic_utils.py
sagemaker_studio_analytics_extension/utils/exceptions.py
sagemaker_studio_analytics_extension/utils/kerberos_reset_util.py
sagemaker_studio_analytics_extension/utils/logging_utils.py
sagemaker_studio_analytics_extension/utils/magic_execution_context.py
sagemaker_studio_analytics_extension/utils/region_utils.py
sagemaker_studio_analytics_extension/utils/resource_check.py
sagemaker_studio_analytics_extension/utils/runtime_check.py
sagemaker_studio_analytics_extension/utils/service_metrics.py
sagemaker_studio_analytics_extension/utils/spark_ui_url_replacer.py
sagemaker_studio_analytics_extension-0.2.2.dist-info/licenses/LICENSE
sagemaker_studio_analytics_extension-0.2.2.dist-info/METADATA
sagemaker_studio_analytics_extension-0.2.2.dist-info/WHEEL
sagemaker_studio_analytics_extension-0.2.2.dist-info/entry_points.txt
sagemaker_studio_analytics_extension-0.2.2.dist-info/top_level.txt
sagemaker_studio_analytics_extension-0.2.2.dist-info/RECORD
