Metadata-Version: 2.4
Name: sagemaker-studio-analytics-extension
Version: 0.2.2
Summary: SageMaker Studio Analytics Extension
Home-page: https://aws.amazon.com/sagemaker
Author: Amazon Web Services
License: Apache 2.0
Classifier: Intended Audience :: Developers
Classifier: Intended Audience :: Science/Research
Classifier: Programming Language :: Python
Classifier: Programming Language :: Python :: 3.7
Classifier: Programming Language :: Python :: 3.8
Classifier: Programming Language :: Python :: 3.10
License-File: LICENSE
Requires-Dist: boto3<2.0,>=1.26.49
Requires-Dist: sparkmagic==0.22.0
Requires-Dist: sagemaker_studio_sparkmagic_lib>=0.1.1
Requires-Dist: sagemaker-jupyterlab-extension-common<1.0,>=0.2.2
Requires-Dist: filelock>=3.0.12
Dynamic: author
Dynamic: classifier
Dynamic: description
Dynamic: description-content-type
Dynamic: home-page
Dynamic: license
Dynamic: license-file
Dynamic: requires-dist
Dynamic: summary
